unmixer/__init__.py
unmixer/__main__.py
unmixer/constants.py
unmixer/remix.py
unmixer/ui/__init__.py
unmixer/ui/constants.py
unmixer/ui/importer.py
unmixer/ui/main.py
unmixer/ui/multitrack.py
unmixer/ui/preferences.py
unmixer/ui/track.py
unmixer/ui/waveform.py
unmixer/util.py
unmixer-1.2.0.dist-info/LICENSE
unmixer-1.2.0.dist-info/METADATA
unmixer-1.2.0.dist-info/WHEEL
unmixer-1.2.0.dist-info/entry_points.txt
unmixer-1.2.0.dist-info/RECORD
