Metadata-Version: 2.1
Name: unmixer
Version: 1.2.0
Summary: Create and explore isolated tracks from music files
Home-page: https://github.com/will2dye4/unmixer.git
License: MIT
Keywords: demux,demux music,music source separation,split,split music,unmix,unmix music,unmixer
Author: William Dye
Requires-Python: >=3.11,<3.13
Classifier: License :: OSI Approved :: MIT License
Classifier: Programming Language :: Python :: 3
Classifier: Programming Language :: Python :: 3.11
Requires-Dist: demucs (>=4.0.1,<5.0.0)
Requires-Dist: ffmpeg-python (>=0.2.0,<0.3.0)
Requires-Dist: numpy (>=1.26.0,<2.0.0)
Requires-Dist: pyqt6 (>=6.5.2,<7.0.0)
Requires-Dist: soundfile (>=0.12.1,<0.13.0)
Requires-Dist: torch (>=2.1.0,<3.0.0)
Project-URL: Repository, https://github.com/will2dye4/unmixer.git
